torchness/__init__.py
torchness/base.py
torchness/batcher.py
torchness/ckpt.py
torchness/devices.py
torchness/encoders.py
torchness/grad_clipping.py
torchness/initialize.py
torchness/layers.py
torchness/motorch.py
torchness/nnmodule.py
torchness/onnx_export.py
torchness/scaled_LR.py
torchness/tbwr.py
torchness/tools.py
torchness/zeroes_processor.py
torchness/models/__init__.py
torchness/models/simple_feats_classifier.py
torchness/models/simple_text_classifier.py
torchness/models/text_embbeder.py
torchness-2.0.1.dist-info/METADATA
torchness-2.0.1.dist-info/WHEEL
torchness-2.0.1.dist-info/top_level.txt
torchness-2.0.1.dist-info/RECORD
