Metadata-Version: 2.1
Name: torchness
Version: 2.0.1
Summary: PyTorch tools
Home-page: https://github.com/piteren/torchness.git
Author: Piotr Niewinski
Author-email: pioniewinski@gmail.com
License: MIT
Requires-Dist: GPUtil
Requires-Dist: numpy
Requires-Dist: ompr
Requires-Dist: onnx
Requires-Dist: onnxruntime
Requires-Dist: pillow
Requires-Dist: pypaq
Requires-Dist: tqdm
Requires-Dist: scikit-learn
Requires-Dist: sentence-transformers
Requires-Dist: tensorboard
Requires-Dist: torch
